octopype/__init__.py
octopype/account/__init__.py
octopype/account/getInfo.py
octopype/account/status_checker.py
octopype/account/update.py
octopype/errors/account.py
octopype/errors/general.py
octopype/errors/repos.py
octopype/repos/__init__.py
octopype/repos/getrepo.py
octopype-0.1.0.dist-info/LICENSE
octopype-0.1.0.dist-info/METADATA
octopype-0.1.0.dist-info/WHEEL
octopype-0.1.0.dist-info/top_level.txt
octopype-0.1.0.dist-info/RECORD
