Metadata-Version: 2.1
Name: octopype
Version: 0.1.0
Summary: GitHub API Wrapper written in Python.
Home-page: https://github.com/BLUEAMETHYST-Studios/octopype
Author: BLUEAMETHYST-Studios
Maintainer: BLUEAMETHYST-Studios
Keywords: github,api,wrapper,http
Classifier: Development Status :: 2 - Pre-Alpha
Classifier: Intended Audience :: Developers
Classifier: License :: OSI Approved
Classifier: License :: OSI Approved :: GNU General Public License v3 (GPLv3)
Classifier: Environment :: Console
Classifier: Natural Language :: English
Classifier: Operating System :: Microsoft :: Windows
Classifier: Operating System :: POSIX :: Linux
Classifier: Operating System :: MacOS :: MacOS X
Classifier: Programming Language :: Python
Classifier: Programming Language :: Python :: 3
Classifier: Topic :: Internet
Classifier: Topic :: Internet :: WWW/HTTP
License-File: LICENSE
